traffic_light.v
module traffic_light(
    input clk,
    input rst,
    output reg R,
    output reg Y,
    output reg G
);

    reg [1:0] state;
    reg [3:0] timer;

    parameter GREEN  = 2'b00,
              YELLOW = 2'b01,
              RED    = 2'b10;

    always @(posedge clk or posedge rst) begin
        if (rst) begin
            state <= GREEN;
            timer <= 0;
        end else begin
            timer <= timer + 1;

            case (state)
                GREEN:  if (timer == 5) begin state <= YELLOW; timer <= 0; end
                YELLOW: if (timer == 2) begin state <= RED;    timer <= 0; end
                RED:    if (timer == 5) begin state <= GREEN;  timer <= 0; end
            endcase
        end
    end

    always @(*) begin
        R = 0; Y = 0; G = 0;

        case (state)
            GREEN:  G = 1;
            YELLOW: Y = 1;
            RED:    R = 1;
        endcase
    end

endmodule

tb_traffic_light.v
`timescale 1ns/1ps

module tb_traffic_light;

    reg clk;
    reg rst;
    wire R, Y, G;

    traffic_light uut (
        .clk(clk),
        .rst(rst),
        .R(R),
        .Y(Y),
        .G(G)
    );

    always #5 clk = ~clk;

    initial begin
        clk = 0;
        rst = 1;
        #10 rst = 0;
        #200 $finish;
    end

    initial begin
        $dumpfile("traffic_light.vcd");
        $dumpvars(0, tb_traffic_light);
    end

endmodule

traffic_light.vcd
$date
	Thu Apr 23 20:54:11 2026
$end
$version
	Icarus Verilog
$end
$timescale
	1ps
$end
$scope module tb_traffic_light $end
$var wire 1 ! Y $end
$var wire 1 " R $end
$var wire 1 # G $end
$var reg 1 $ clk $end
$var reg 1 % rst $end
$scope module uut $end
$var wire 1 $ clk $end
$var wire 1 % rst $end
$var parameter 2 & GREEN $end
$var parameter 2 ' RED $end
$var parameter 2 ( YELLOW $end
$var reg 1 # G $end
$var reg 1 " R $end
$var reg 1 ! Y $end
$var reg 2 ) state [1:0] $end
$var reg 4 * timer [3:0] $end
$upscope $end
$upscope $end
$enddefinitions $end
$comment Show the parameter values. $end
$dumpall
b1 (
b10 '
b0 &
$end
#0
$dumpvars
b0 *
b0 )
1%
0$
1#
0"
0!
$end
#5000
1$
#10000
0$
0%
#15000
b1 *
1$
#20000
0$
#25000
b10 *
1$
#30000
0$
#35000
b11 *
1$
#40000
0$
#45000
b100 *
1$
#50000
0$
#55000
b101 *
1$
#60000
0$
#65000
1!
0#
b1 )
b0 *
1$
#70000
0$
#75000
b1 *
1$
#80000
0$
#85000
b10 *
1$
#90000
0$
#95000
1"
0!
b10 )
b0 *
1$
#100000
0$
#105000
b1 *
1$
#110000
0$
#115000
b10 *
1$
#120000
0$
#125000
b11 *
1$
#130000
0$
#135000
b100 *
1$
#140000
0$
#145000
b101 *
1$
#150000
0$
#155000
1#
0"
b0 )
b0 *
1$
#160000
0$
#165000
b1 *
1$
#170000
0$
#175000
b10 *
1$
#180000
0$
#185000
b11 *
1$
#190000
0$
#195000
b100 *
1$
#200000
0$
#205000
b101 *
1$
